{
    "id": 1125,
    "title": "Smallest Sufficient Team",
    "title_slug": "smallest-sufficient-team",
    "backend_id": 1220,
    "content": [
        [
            "project",
            "list",
            "require",
            "skill",
            "list"
        ],
        [
            "th",
            "person",
            "contain",
            "list",
            "skill",
            "person"
        ],
        [
            "consider",
            "sufficient",
            "team",
            "set",
            "people",
            "every",
            "require",
            "skill",
            "least",
            "one",
            "person",
            "team",
            "skill"
        ],
        [
            "represent",
            "team",
            "index",
            "person",
            "example",
            "represent",
            "people",
            "skill"
        ],
        [
            "return",
            "sufficient",
            "team",
            "small",
            "possible",
            "size",
            "represent",
            "index",
            "person"
        ],
        [
            "may",
            "return",
            "answer",
            "order"
        ],
        [
            "guarantee",
            "answer",
            "exist"
        ],
        [
            "element",
            "respectively",
            "distinct"
        ],
        [
            "lowercase",
            "english",
            "letter"
        ],
        [
            "every",
            "skill",
            "skill"
        ],
        [
            "guarantee",
            "sufficient",
            "team",
            "exist"
        ]
    ]
}